bacpack/__init__.py
bacpack/bac.py
bacpack/bacpack.py
bacpack/empiricbac.py
bacpack/highfreq.py
bacpack/simulation.py
bacpack/toy.py
bacpack-0.0.25.dist-info/METADATA
bacpack-0.0.25.dist-info/WHEEL
bacpack-0.0.25.dist-info/top_level.txt
bacpack-0.0.25.dist-info/RECORD
