Metadata-Version: 2.1
Name: bacpack
Version: 0.0.25
Summary: Beta Adjusted Covariance estimation
Home-page: UNKNOWN
Author: Kirill Dragun, Kris Boudt
Author-email: kdragun@vub.be, kris.boudt@vub.be
License: UNKNOWN
Keywords: BAC estimator highfrequency high frequency bacpack
Platform: UNKNOWN
Requires-Dist: numpy
Requires-Dist: pandas
Requires-Dist: numba
